repo2podman/__init__.py
repo2podman/_version.py
repo2podman/podman.py
repo2podman-0.2.0.dist-info/LICENSE
repo2podman-0.2.0.dist-info/METADATA
repo2podman-0.2.0.dist-info/WHEEL
repo2podman-0.2.0.dist-info/entry_points.txt
repo2podman-0.2.0.dist-info/top_level.txt
repo2podman-0.2.0.dist-info/RECORD
