Metadata-Version: 2.1
Name: repo2podman
Version: 0.2.0
Summary: Repo2docker Podman extension
Home-page: https://github.com/manics/repo2podman
Author: Simon Li
License: BSD
Project-URL: Documentation, https://repo2docker.readthedocs.io
Keywords: reproducible science environments docker
Classifier: Environment :: Console
Classifier: Intended Audience :: Developers
Classifier: Intended Audience :: System Administrators
Classifier: Intended Audience :: Science/Research
Classifier: License :: OSI Approved :: BSD License
Classifier: Programming Language :: Python
Classifier: Programming Language :: Python :: 3
Requires-Python: >=3.6
License-File: LICENSE
Requires-Dist: jupyter-repo2docker >=2021.08.0
Requires-Dist: docker-image-py
